wallpaper_mcp/__init__.py
wallpaper_mcp/__main__.py
wallpaper_mcp/server.py
wallpaper_mcp/wallpaper.py
wallpaper_mcp-0.1.1.dist-info/METADATA
wallpaper_mcp-0.1.1.dist-info/WHEEL
wallpaper_mcp-0.1.1.dist-info/entry_points.txt
wallpaper_mcp-0.1.1.dist-info/licenses/LICENSE
wallpaper_mcp-0.1.1.dist-info/RECORD
