Metadata-Version: 2.4
Name: wallpaper-mcp
Version: 0.1.1
Summary: MCP server for setting desktop wallpaper across Windows, macOS and Linux
Project-URL: Homepage, https://github.com/mcpcn/wallpaper-mcp
Project-URL: Bug Tracker, https://github.com/mcpcn/wallpaper-mcp/issues
Project-URL: Documentation, https://github.com/mcpcn/wallpaper-mcp#readme
Author-email: MCP Chinese Community <tech@mcp.cn>
License-Expression: MIT
License-File: LICENSE
Keywords: cross-platform,desktop,linux,macos,mcp,wallpaper,windows
Classifier: Development Status :: 4 - Beta
Classifier: Intended Audience :: Developers
Classifier: License :: OSI Approved :: MIT License
Classifier: Operating System :: MacOS
Classifier: Operating System :: Microsoft :: Windows
Classifier: Operating System :: OS Independent
Classifier: Operating System :: POSIX :: Linux
Classifier: Programming Language :: Python :: 3
Classifier: Programming Language :: Python :: 3.10
Classifier: Programming Language :: Python :: 3.11
Classifier: Programming Language :: Python :: 3.12
Classifier: Topic :: Desktop Environment
Classifier: Topic :: Software Development :: Libraries :: Python Modules
Requires-Python: >=3.10
Requires-Dist: mcp>=0.9.0
Requires-Dist: pillow>=10.0.0
Requires-Dist: requests>=2.31.0
Provides-Extra: dev
Requires-Dist: black>=23.0.0; extra == 'dev'
Requires-Dist: pytest-asyncio>=0.21.0; extra == 'dev'
Requires-Dist: pytest>=7.4.0; extra == 'dev'
Requires-Dist: ruff>=0.1.0; extra == 'dev'
